extepy/__init__.py
extepy/_collect.py
extepy/_fill.py
extepy/_fun.py
extepy/_hash.py
extepy/_import.py
extepy/_op.py
extepy/_seq.py
extepy/_version.py
extepy-1.0.0.dist-info/licenses/LICENSE
extepy-1.0.0.dist-info/METADATA
extepy-1.0.0.dist-info/WHEEL
extepy-1.0.0.dist-info/top_level.txt
extepy-1.0.0.dist-info/RECORD
