Metadata-Version: 2.4
Name: extepy
Version: 1.0.0
Summary: Extension of Python Language
Home-page: http://github.com/extepy/extepy
Author: Zhiqing Xiao
Author-email: zhiqingxiaophd@gmail.com
Classifier: Programming Language :: Python
License-File: LICENSE
Dynamic: author
Dynamic: author-email
Dynamic: classifier
Dynamic: description
Dynamic: description-content-type
Dynamic: home-page
Dynamic: license-file
Dynamic: summary
